synthpop/__init__.py
synthpop/categorizer.py
synthpop/census_helpers.py
synthpop/draw.py
synthpop/synthesizer.py
synthpop/zone_synthesizer.py
synthpop/ipf/__init__.py
synthpop/ipf/ipf.py
synthpop/ipf/test/__init__.py
synthpop/ipf/test/test_ipf.py
synthpop/ipu/__init__.py
synthpop/ipu/ipu.py
synthpop/ipu/test/__init__.py
synthpop/ipu/test/test_ipu.py
synthpop/recipes/__init__.py
synthpop/recipes/starter.py
synthpop/recipes/starter2.py
synthpop/test/__init__.py
synthpop/test/test_categorizer.py
synthpop/test/test_censushelpers.py
synthpop/test/test_draw.py
synthpop/test/test_zone_synthesizer.py
synthpop-0.1.1.dist-info/METADATA
synthpop-0.1.1.dist-info/RECORD
synthpop-0.1.1.dist-info/WHEEL
synthpop-0.1.1.dist-info/top_level.txt
