Metadata-Version: 2.1
Name: synthpop
Version: 0.1.1
Summary: Population Synthesis
Home-page: https://github.com/udst/synthpop
Author: UrbanSim Inc.
Author-email: udst@urbansim.com
License: BSD
Platform: UNKNOWN
Classifier: Development Status :: 4 - Beta
Classifier: Programming Language :: Python :: 2.7
Classifier: Programming Language :: Python :: 3.5
Classifier: Programming Language :: Python :: 3.6
Requires-Dist: census (>=0.5)
Requires-Dist: numexpr (>=2.3.1)
Requires-Dist: numpy (>=1.8.0)
Requires-Dist: pandas (>=0.15.0)
Requires-Dist: scipy (>=0.13.3)
Requires-Dist: us (>=0.8)
